dj_access_logger/__init__.py
dj_access_logger/admin.py
dj_access_logger/apps.py
dj_access_logger/db_router.py
dj_access_logger/default_settings.py
dj_access_logger/methods.py
dj_access_logger/middleware.py
dj_access_logger/models.py
dj_access_logger/utils.py
dj_access_logger/loggers/__init__.py
dj_access_logger/loggers/abstract_logger.py
dj_access_logger/loggers/file_logger.py
dj_access_logger/loggers/nosql_logger.py
dj_access_logger/loggers/singleton.py
dj_access_logger/loggers/sql_logger.py
dj_access_logger/management/__init__.py
dj_access_logger/management/commands/__init__.py
dj_access_logger/management/commands/setup_dj_access_logger.py
dj_access_logger/migrations/0001_initial.py
dj_access_logger/migrations/0002_accesslog_ipv4_address_accesslog_ipv6_address.py
dj_access_logger/migrations/__init__.py
dj_access_logger/repositories/__init__.py
dj_access_logger/repositories/repositories.py
dj_access_logger/tests/__init__.py
dj_access_logger/tests/test_middleware.py
dj_access_logger-1.0.5.dist-info/METADATA
dj_access_logger-1.0.5.dist-info/WHEEL
dj_access_logger-1.0.5.dist-info/top_level.txt
dj_access_logger-1.0.5.dist-info/RECORD
