Metadata-Version: 2.1
Name: dj-access-logger
Version: 1.0.5
Summary: A Django middleware for logging HTTP requests and responses.
Home-page: https://github.com/elkhayyat/dj-access-logger
Author: AHMED ELKHAYYAT
Author-email: elkhayyat.me@gmail.com
License: MIT License
Classifier: Environment :: Web Environment
Classifier: Framework :: Django
Classifier: Intended Audience :: Developers
Classifier: License :: OSI Approved :: MIT License
Classifier: Operating System :: OS Independent
Classifier: Programming Language :: Python
Classifier: Programming Language :: Python :: 3
Classifier: Topic :: Internet :: WWW/HTTP
Classifier: Topic :: Internet :: WWW/HTTP :: Dynamic Content
Requires-Dist: Django (>=3.0)
Requires-Dist: pymongo
Requires-Dist: djongo
Requires-Dist: mysqlclient
Requires-Dist: psycopg2
Requires-Dist: pygments
